.travis.yml
README.rst
setup.py
tox.ini
mr/__init__.py
mr.awsome.fabric.egg-info/PKG-INFO
mr.awsome.fabric.egg-info/SOURCES.txt
mr.awsome.fabric.egg-info/dependency_links.txt
mr.awsome.fabric.egg-info/entry_points.txt
mr.awsome.fabric.egg-info/namespace_packages.txt
mr.awsome.fabric.egg-info/not-zip-safe
mr.awsome.fabric.egg-info/requires.txt
mr.awsome.fabric.egg-info/top_level.txt
mr/awsome_fabric/__init__.py
mr/awsome_fabric/fabric_integration.py
mr/awsome_fabric/test_fabric.py