Metadata-Version: 1.0
Name: mr.awsome.fabric
Version: 1.0b3
Summary: A plugin for mr.awsome providing integration with Fabric.
Home-page: http://github.com/fschulze/mr.awsome.fabric
Author: Florian Schulze
Author-email: florian.schulze@gmx.net
License: UNKNOWN
Platform: UNKNOWN
